passflip
