Metadata-Version: 1.0
Name: passflip
Version: 0.7
Summary: Command line tool to mutate passwords for different websites.
Home-page: https://www.github.com/byxor/passflip
Author: Brandon Ibbotson
Author-email: brandon.ibbotson2@mail.dcu.ie
License: GPLv3
Platform: UNKNOWN
